{
  "paper_metadata": {
    "pmid": "34638656",
    "title": "MAIN TEXT",
    "extraction_summary": "No variants in the KCNH2 gene were mentioned in the provided text."
  },
  "variants": [],
  "tables_processed": [],
  "extraction_metadata": {
    "total_variants_found": 0,
    "extraction_confidence": "high",
    "challenges": [
      "The provided text did not contain any mention of KCNH2 gene variants."
    ],
    "notes": "The extraction was straightforward as there were no mentions of the KCNH2 gene variants in the text."
  }
}