{
  "paper_metadata": {
    "pmid": "34242301",
    "title": "MAIN TEXT",
    "extraction_summary": "The paper discusses the prevalence and clinical characteristics of transthyretin cardiac amyloidosis (ATTR-CA) among patients with unexplained heart failure and systolic LV dysfunction. No specific genetic variants in the TTR gene were reported."
  },
  "variants": [],
  "tables_processed": [],
  "extraction_metadata": {
    "total_variants_found": 0,
    "extraction_confidence": "high",
    "challenges": [
      "The paper did not report any specific genetic variants in the TTR gene."
    ],
    "notes": "The paper focused on clinical and diagnostic aspects of ATTR-CA without detailing specific genetic variants in the TTR gene."
  }
}